textcluster/__init__.py
textcluster/cluster.py
textcluster/search.py
textcluster/tests.py
textcluster-0.0.2.dist-info/DESCRIPTION.rst
textcluster-0.0.2.dist-info/METADATA
textcluster-0.0.2.dist-info/pydist.json
textcluster-0.0.2.dist-info/RECORD
textcluster-0.0.2.dist-info/top_level.txt
textcluster-0.0.2.dist-info/WHEEL
